metatube/__init__.py
metatube/__main__.py
metatube/cache.py
metatube/config.py
metatube/timespan.py
metatube/youtubecommentthreaddownloader.py
metatube/youtubemetadatadownloader.py
metatube/youtubevideometadatadownloader.py
metatube/models/__init__.py
metatube/models/base.py
metatube/models/channel.py
metatube/models/comment.py
metatube/models/commentthread.py
metatube/models/user.py
metatube/models/video.py
metatube-1.0.6.data/data/metatube.yml.example
metatube-1.0.6.dist-info/LICENSE
metatube-1.0.6.dist-info/METADATA
metatube-1.0.6.dist-info/WHEEL
metatube-1.0.6.dist-info/entry_points.txt
metatube-1.0.6.dist-info/top_level.txt
metatube-1.0.6.dist-info/RECORD
